bmr4pml/__init__.py
bmr4pml/datasets.py
bmr4pml/delta_f.py
bmr4pml/inference.py
bmr4pml/models.py
bmr4pml/utils.py
bmr4pml/nn/__init__.py
bmr4pml/nn/activations.py
bmr4pml/nn/lenet.py
bmr4pml/nn/mlp.py
bmr4pml/nn/resnet.py
bmr4pml/nn/utils.py
bmr4pml/nn/vit.py
bmr4pml-0.1.0.dist-info/LICENSE
bmr4pml-0.1.0.dist-info/METADATA
bmr4pml-0.1.0.dist-info/WHEEL
bmr4pml-0.1.0.dist-info/top_level.txt
bmr4pml-0.1.0.dist-info/RECORD
